CHANGELOG.md
LICENSE
MANIFEST.in
README.md
pyproject.toml
setup.py
dsigma/__init__.py
dsigma/helpers.py
dsigma/jackknife.py
dsigma/physics.py
dsigma/precompute.py
dsigma/precompute_engine.pyx
dsigma/stacking.py
dsigma.egg-info/PKG-INFO
dsigma.egg-info/SOURCES.txt
dsigma.egg-info/dependency_links.txt
dsigma.egg-info/requires.txt
dsigma.egg-info/top_level.txt
dsigma/surveys/__init__.py
dsigma/surveys/cfhtls.py
dsigma/surveys/des.py
dsigma/surveys/hsc.py
dsigma/surveys/kids.py