Metadata-Version: 2.4
Name: dsigma
Version: 1.1.0
Author: Song Huang
Author-email: "Johannes U. Lange" <jlange@american.edu>
License-Expression: MIT
Project-URL: Homepage, https://github.com/johannesulf/dsigma
Project-URL: Documentation, https://dsigma.readthedocs.io
Project-URL: Repository, https://github.com/johannesulf/dsigma.git
Project-URL: Issues, https://github.com/johannesulf/dsigma/issues
Project-URL: Changelog, https://github.com/johannesulf/dsigma/blob/main/CHANGELOG.md
Keywords: astronomy,weak-lensing
Requires-Python: >=3.9
License-File: LICENSE
Requires-Dist: numpy
Requires-Dist: astropy
Requires-Dist: scipy
Requires-Dist: scikit-learn
Requires-Dist: astropy-healpix
Requires-Dist: tqdm
Dynamic: license-file
